spikeweb/__init__.py
spikeweb/spikeweb.py
spikeweb/templates/__init__.py
spikeweb-0.1.0.dist-info/METADATA
spikeweb-0.1.0.dist-info/WHEEL
spikeweb-0.1.0.dist-info/top_level.txt
spikeweb-0.1.0.dist-info/RECORD
