Metadata-Version: 2.1
Name: spikeweb
Version: 0.1.0
Summary: creating a web basic folder struture requirment
Author: saber_x123
Author-email: yoyue@happy@gmail.com
Classifier: Programming Language :: Python :: 3
Classifier: License :: OSI Approved :: MIT License
Classifier: Operating System :: OS Independent
Requires-Dist: requests
